{
    "name": "Template infrasrtructure",

    "nodes":
    [
        {
            "id": "aaa",
            "n_core": 6,
            "core_frequency": "1.5G",
            "p_static": 1,
            "k": 1,
            "alpha": 1
        },
        {
            "id": "bbb",
            "n_core": 6,
            "core_frequency": "1.6G",
            "p_static": 2,
            "k": 2,
            "alpha": 2
        },
        {
            "id": "ccc",
            "n_core": 6,
            "core_frequency": "1.8G",
            "p_static": 2,
            "k": 2,
            "alpha": 2
        }
    ],

    "edges":
    [
        {
            "from": "aaa",
            "to": "bbb",
            "resource": "1G"
        },
        {
            "from": "bbb",
            "to": "ccc",
            "resource": "1G"
        },
        {
            "from": "aaa",
            "to": "ccc",
            "resource": "1G"
        }
    ]
}